{
    "translations": {
        "de": {
            "Type": "Typ",
            "<none>": "<keiner>",
            "PPP (DSL)": "PPP (DSL)",
            "IP (Cable)": "IP (Kabel)",
            "Refresh Interval": "Aktualisierungsintervall",
            "seconds": "Sekunden",
            "Update Values": "Werte aktualisieren",
            "Event subscribe error": "Ereignisabonnementfehler",
            "Invalid Ident.": "Ungültiger Ident.",
            "Number of port mapping": "Anzahl der Port Mappings",
            "Only port forwarding of IP addresses of the Symcon server can be switched!": "Es können nur Portweiterleitungen von IP-Adressen des Symcon Server geschaltet werden!",
            "This module is free for non-commercial use,\r\nDonations in support of the author are accepted here:": "Dieses Modul ist für die nicht kommerzielle Nutzung kostenlos,\r\nSchenkungen als Unterstützung für den Autor werden hier akzeptiert:"
        }
    }
}