{
    "translations": {
        "de": {
            "Not connected!": "Nicht verbunden!",
            "The 'FritzBox IO' instance is not connected or missing.": "Die 'FritzBox IO' Instanz ist nicht verbunden oder fehlt.",
            "The call monitor is not activated on the FritzBox, or is blocked by something.": "Der Anrufmonitor ist auf der FritzBox nicht aktiviert, oder durch irgendetwas blockiert.",
            "FritzBox Telephony": "FritzBox Telefonie",
            "FritzBox Callmonitor": "FritzBox Anrufmonitor",
            "FritzBox Device Info": "FritzBox Geräteinformationen",
            "FritzBox DHCP Server": "FritzBox DHCP Server",
            "FritzBox DynDns": "FritzBox DynDns",
            "FritzBox File Share": "FritzBox Dateifreigabe",
            "FritzBox Hosts": "FritzBox Netzwerkgeräte",
            "FritzBox MyFritz": "FritzBox MyFritz",
            "FritzBox NAS Storage": "FritzBox NAS Storage",
            "FritzBox Time": "FritzBox Zeitserver",
            "FritzBox UPnP MediaServer": "FritzBox UPnP MediaServer",
            "FritzBox WAN Common Interface": "FritzBox allgemeine WAN-Schnittstelle",
            "FritzBox WAN DSL Link": "FritzBox WAN DSL-Verbindung",
            "FritzBox WAN IP Connection": "FritzBox WAN IP-Verbindung",
            "FritzBox WAN Port Mapping": "FritzBox WAN Port-Weiterleitung",
            "FritzBox WAN Physical Interface": "FritzBox physikalische WAN-Schnittstelle",
            "FritzBox WebDav Storage": "FritzBox Online-Speicher",
            "FritzBox WLAN": "FritzBox WLAN",
            "Events": "Ereignisse",
            "no": "Nein",
            "yes": "Ja",
            "This module is free for non-commercial use,\r\nDonations in support of the author are accepted here:": "Dieses Modul ist für die nicht kommerzielle Nutzung kostenlos,\r\nSchenkungen als Unterstützung für den Autor werden hier akzeptiert:"
        }
    }
}