{
    "translations": {
        "de": {
            "Service": "Dienst",
            "<none>": "<keiner>",
            "Refresh Interval": "Aktualisierungsintervall",
            "Refresh Linkstate Interval": "Aktualisierungsintervall Linkstatus",
            "seconds": "Sekunden",
            "Update Values": "Werte aktualisieren",
            "Update Linkstate": "Linkstatus aktualisieren",
            "Event subscribe error": "Ereignisabonnementfehler",
            "Invalid Ident.": "Ungültiger Ident.",
            "Fiber": "Glasfaser",
            "Cable": "Kabelanschluss",
            "Other": "Anders",
            "Up": "Verbunden",
            "Down": "Getrennt",
            "Initializing": "Initialisieren",
            "Unavailable": "Nicht verfügbar",
            "WAN Access type": "WAN Zugangsart",
            "Physical Link Status": "Status der physischen Verbindung",
            "Upstream Max kBitrate": "Upstream Max kBitrate",
            "Downstream Max kBitrate": "Downstream Max kBitrate",
            "Sending rate": "Senderate",
            "Receive rate": "Empfangsrate",
            "Load download": "Auslastung Download",
            "Load upload": "Auslastung Upload",
            "Sent since connected": "Gesendet seit verbunden",
            "Received since connected": "Empfangen seit verbunden",
            "Allow automatic port forwarding via UPnP": "Automatische Portweiterleitung per UPnP erlauben",
            "DNS-Server 1": "DNS-Server 1",
            "DNS-Server 2": "DNS-Server 2",
            "VoIP DNS-Server 1": "VoIP DNS-Server 1",
            "VoIP DNS-Server 2": "VoIP DNS-Server 2",
            "This module is free for non-commercial use,\r\nDonations in support of the author are accepted here:": "Dieses Modul ist für die nicht kommerzielle Nutzung kostenlos,\r\nSchenkungen als Unterstützung für den Autor werden hier akzeptiert:"
        }
    }
}